blender_open_mcp/__init__.py
blender_open_mcp/server.py
mseep_blender_open_mcp-0.2.4.dist-info/licenses/LICENSE
mseep_blender_open_mcp-0.2.4.dist-info/METADATA
mseep_blender_open_mcp-0.2.4.dist-info/WHEEL
mseep_blender_open_mcp-0.2.4.dist-info/entry_points.txt
mseep_blender_open_mcp-0.2.4.dist-info/top_level.txt
mseep_blender_open_mcp-0.2.4.dist-info/RECORD
