Metadata-Version: 2.4
Name: mseep-blender-open-mcp
Version: 0.2.4
Summary: Blender integration with local AI models via MCP and Ollama
Author-email: mseep <support@skydeck.ai>
License: MIT
Project-URL: Homepage, https://github.com/dhakalnirajan/blender-open-mcp
Project-URL: Bug Tracker, https://github.com/dhakalnirajan/blender-open-mcp/issues
Classifier: Programming Language :: Python :: 3
Classifier: License :: OSI Approved :: MIT License
Classifier: Operating System :: OS Independent
Requires-Python: >=3.10
License-File: LICENSE
Requires-Dist: mcp[cli]>=1.3.0
Requires-Dist: httpx>=0.24.0
Requires-Dist: ollama>=0.4.7
Dynamic: license-file
